langchain_glean/__init__.py
langchain_glean/_api_client_mixin.py
langchain_glean/py.typed
langchain_glean/toolkit.py
langchain_glean/chat_models/__init__.py
langchain_glean/chat_models/agent_chat.py
langchain_glean/chat_models/chat.py
langchain_glean/retrievers/__init__.py
langchain_glean/retrievers/people.py
langchain_glean/retrievers/search.py
langchain_glean/tools/__init__.py
langchain_glean/tools/chat.py
langchain_glean/tools/get_agent_schema.py
langchain_glean/tools/list_agents.py
langchain_glean/tools/people_profile_search.py
langchain_glean/tools/run_agent.py
langchain_glean/tools/search.py
langchain_glean-0.3.4.dist-info/METADATA
langchain_glean-0.3.4.dist-info/WHEEL
langchain_glean-0.3.4.dist-info/licenses/LICENSE
langchain_glean-0.3.4.dist-info/RECORD
