Metadata-Version: 2.4
Name: langchain-glean
Version: 0.3.4
Summary: An integration package connecting Glean and LangChain
Project-URL: Source Code, https://github.com/langchain-ai/langchain/tree/master/libs/partners/glean
Project-URL: Release Notes, https://github.com/langchain-ai/langchain/releases?q=tag%3A%22glean%3D%3D0%22&expanded=true
Author-email: John Agan <john.agan@glean.com>, Steve Calvert <steve.calvert@glean.com>
License: MIT
License-File: LICENSE
Requires-Python: <4.0,>=3.9
Requires-Dist: glean-api-client<0.12,>=0.11
Requires-Dist: langchain-core>=0.3.45
Provides-Extra: codespell
Requires-Dist: codespell>=2.2.6; extra == 'codespell'
Provides-Extra: dev
Requires-Dist: commitizen>=4.4.1; extra == 'dev'
Provides-Extra: lint
Requires-Dist: ruff>=0.5; extra == 'lint'
Provides-Extra: test
Requires-Dist: langchain-tests>=0.3.5; extra == 'test'
Requires-Dist: pytest-asyncio>=0.23.2; extra == 'test'
Requires-Dist: pytest-socket>=0.7.0; extra == 'test'
Requires-Dist: pytest-watcher>=0.3.4; extra == 'test'
Requires-Dist: pytest>=7.4.3; extra == 'test'
Requires-Dist: python-dotenv>=1.1.0; extra == 'test'
Provides-Extra: test-integration
Provides-Extra: typing
Requires-Dist: mypy>=1.10; extra == 'typing'
Requires-Dist: types-requests>=2.31.0.1; extra == 'typing'
